h2ohyperopt/__init__.py
h2ohyperopt/dleoptimizer.py
h2ohyperopt/examples.py
h2ohyperopt/gbmoptimizer.py
h2ohyperopt/glmoptimizer.py
h2ohyperopt/modeldocker.py
h2ohyperopt/modeloptimizer.py
h2ohyperopt/util.py
h2ohyperopt/tests/__init__.py
h2ohyperopt/tests/data_gen.py
h2ohyperopt/tests/test_DLEOpt.py
h2ohyperopt/tests/test_GBMOpt.py
h2ohyperopt/tests/test_GLMOpt.py
h2ohyperopt/tests/test_ModelDockerOpt.py
h2ohyperopt/tests/test_modelOpt_metrics.py
h2ohyperopt/tests/test_modelOpt_parameters.py
h2ohyperopt/tests/test_util.py
h2ohyperopt-0.3.dist-info/DESCRIPTION.rst
h2ohyperopt-0.3.dist-info/METADATA
h2ohyperopt-0.3.dist-info/RECORD
h2ohyperopt-0.3.dist-info/WHEEL
h2ohyperopt-0.3.dist-info/metadata.json
h2ohyperopt-0.3.dist-info/top_level.txt
